Metadata-Version: 2.1
Name: PyLanguageEasySeperated
Version: 1.0.1
Summary: PyLanguageEasySeperated
Author: Developer HelloUsers
Author-email: duartesaopedrocat1@gmail.com
Keywords: python,Pylan,pylan,EasyPython,EasyPyLan,easypylan,pygame,game,image
Classifier: Development Status :: 5 - Production/Stable
Classifier: Intended Audience :: Developers
Classifier: Programming Language :: Python :: 3
Classifier: Operating System :: Unix
Classifier: Operating System :: MacOS :: MacOS X
Classifier: Operating System :: Microsoft :: Windows
License-File: LICENSE
